pyproject.toml
exam_pp/__init__.py
exam_pp/data_model.py
exam_pp/davinci_to_runs_with_text.py
exam_pp/exam_cover_metric.py
exam_pp/exam_evaluation.py
exam_pp/exam_grading.py
exam_pp/exam_judgment_correlation.py
exam_pp/exam_leaderboard_analysis.py
exam_pp/exam_leaderboard_correlation.py
exam_pp/exam_on_the_fly.py
exam_pp/exam_post_pipeline.py
exam_pp/exam_run_trec_eval.py
exam_pp/exam_to_qrels.py
exam_pp/exam_verification.py
exam_pp/exam_verify_answer.py
exam_pp/gpt_cost_estimate.py
exam_pp/ir_datasets_test.py
exam_pp/mytest.py
exam_pp/openai_car_run.py
exam_pp/openai_interface.py
exam_pp/print_correlation_table.py
exam_pp/py.typed
exam_pp/pydantic_helper.py
exam_pp/query_loader.py
exam_pp/question_bank_loader.py
exam_pp/question_generation.py
exam_pp/question_loader.py
exam_pp/t5_qa.py
exam_pp/test_bank_prompts.py
exam_pp/tqa_loader.py
exam_pp.egg-info/PKG-INFO
exam_pp.egg-info/SOURCES.txt
exam_pp.egg-info/dependency_links.txt
exam_pp.egg-info/entry_points.txt
exam_pp.egg-info/requires.txt
exam_pp.egg-info/top_level.txt